setup.cfg
setup.py
aqua_io/__init__.py
aqua_io/client.py
aqua_io.egg-info/PKG-INFO
aqua_io.egg-info/SOURCES.txt
aqua_io.egg-info/dependency_links.txt
aqua_io.egg-info/requires.txt
aqua_io.egg-info/top_level.txt
aqua_io/api/__init__.py
aqua_io/api/access_token.py
aqua_io/api/icd10.py
aqua_io/api/icd9.py
aqua_io/error/__init__.py
aqua_io/error/client_error.py
aqua_io/http_client/__init__.py
aqua_io/http_client/auth_handler.py
aqua_io/http_client/error_handler.py
aqua_io/http_client/request_handler.py
aqua_io/http_client/response.py
aqua_io/http_client/response_handler.py