Metadata-Version: 1.1
Name: aqua-io
Version: 0.1.0
Summary: Official Aqua.io API library client for Python
Home-page: https://aqua.io
Author: Michael Carroll / Aqua.io
Author-email: michael@aqua.io
License: MIT
Download-URL: https://github.com/Aquaio/aqua-io-python/tarball/0.1
Keywords: aqua,aqua.io,api,client,library,ICD,ICD9,ICD10,ICD-9,ICD-10,meaningful use,healthcare,health,EHR,EMR,medicine,medical
Platform: UNKNOWN
Classifier: Development Status :: 5 - Production/Stable
Classifier: Intended Audience :: Developers
Classifier: License :: OSI Approved :: MIT License
Classifier: Operating System :: OS Independent
Classifier: Programming Language :: Python :: 2.6
Classifier: Programming Language :: Python :: 2.7
Classifier: Programming Language :: Python :: 3.2
Classifier: Programming Language :: Python :: 3.3
Classifier: Topic :: Software Development :: Libraries :: Python Modules
